{"posts_2023_11_open-source-app-music-player.md":"u5ngknHN","posts_2023_09_open-source-simple-music-player.md":"ZIXF-EN0","prepare_floating-vue.md":"7y9G5HCg","posts_2024_01_3.vue3 子传父 (自定义方法).md":"hgzkYF1m","posts_2024_01_2.vue3 父传子(自定义属性).md":"FnZBn45Q","posts_2024_01_5.vue3defineexpose 的使用.md":"WDT_o_5V","prepare_open-source-web-bbs.md":"CiG5UKph","posts_2024_01_9.vue3和vue2 v-model 和sync语法糖区别.md":"a9IidMm5","prepare_iphone-pro-15-3d-mockups-free.md":"QZGGmjWQ","posts_2024_01_8.vue3 侦听路由的 route.params.id 的变化 .md":"3EEqFkik","posts_2023_10_open-source-by-api-app.md":"gIvMjTi4","index.md":"KWtmqVqk","posts_2024_01_6.vue3使用v-model 自定义组件封装.md":"v1QZQmHy","prepare_v-shared-element.md":"WyZdqPlR","posts_2024_01_14.vue.set()和this._set()介绍 为解决vue2受 es5 的限制，vue2 不能检测到对象属性的添加或删除.md":"iZKCyyGK","prepare_qrcode-toolkit.md":"QQZb99d5","posts_2023_09_open-source-travl-wechatapp.md":"Rkykpz33","posts_2023_12_open-source-todo-wechatapp.md":"fqJV0olt","pages_feed.md":"LnHriFri","pages_archives.md":"uGScmtEJ","posts_2024_01_18.页面首次加载获取 url？后面参数时_不通过 this._route.query 获取参数.md":"ChJpM_XR","posts_2024_01_1.vue3使用reactive函数声明数组如何正确赋值.md":"lVUFTxd6","posts_2023_11_open-source-blog-wechatapp.md":"WgPAqnc1","posts_2024_01_16.vue2 使用sync 数据从 回流_ 封装一个子父双向数据绑定的组件.md":"WM6wifYD","posts_2024_01_17.vue2 的过渡动画.md":"esylx5gs","pages_post.md":"ak62F0aZ","posts_2023_10_freebie-cartoon-avatar-design.md":"m9lZm4-s","pages_about.md":"ycl2RU-t","pages_tags.md":"0SQhvYgJ","posts_2023_12_freebie-iphone15pro-mockups.md":"qOoxui9R","pages_tools.md":"q0Ab5GNH","posts_2024_01_11.vue3——onbeforerouteleave.md":"iNDsVKqo","posts_2023_12_open-source-web-music-player.md":"3QhyKN7t","posts_2024_01_10.vue3 封装个简易的 dialog 对话框 父来展示_子来隐藏.md":"qiq7IxCD","posts_2024_01_15.vue插槽_默认插槽_具名插槽，作用域插槽.md":"zIRGRqoD","posts_2024_01_7.vue3 自定义插件和将属性和方法挂载到全局的使用.md":"Oj8UnS_Y","posts_2024_01_19.vue动态路由刷新丢失解决方案.md":"m5la86Of","posts_2024_01_4.vue3 兄弟传值 ( provide - inject ).md":"4HHyBKUK","posts_2023_09_open-source-avatar-builder.md":"Je5dD37R","pages_links.md":"eSMI_AG1","posts_2023_09_freebie-iphone14pro-mockups.md":"ONvAcfrt","posts_2023_11_open-source-study-wechatapp.md":"-ZOLS42i","posts_2023_10_open-source-web-todo-list.md":"rL6u1Jwu","prepare_open-source-interesting-app.md":"nz299PaM","posts_2024_01_13.vue2 .sync详细理解和父子组件传值方法.md":"2qzQ5LZ3","posts_2024_01_12.vue3 中注册全局组件与自定义指令.md":"t22E6fPi"}
